primetrust
