Metadata-Version: 1.1
Name: primetrust
Version: 1.1.8
Summary: API for primetrust
Home-page: UNKNOWN
Author: Amit Assaraf
Author-email: amit.assaraf@gmail.com
License: MIT
Keywords: setuptools development
Platform: UNKNOWN
Classifier: Development Status :: 3 - Alpha
Classifier: Intended Audience :: Developers
Classifier: Topic :: Software Development :: Build Tools
Classifier: License :: OSI Approved :: MIT License
Classifier: Programming Language :: Python :: 2
Classifier: Programming Language :: Python :: 2.7
